cappy/__init__.py
cappy_grand_creators-0.0.2b0.dist-info/LICENSE
cappy_grand_creators-0.0.2b0.dist-info/METADATA
cappy_grand_creators-0.0.2b0.dist-info/WHEEL
cappy_grand_creators-0.0.2b0.dist-info/top_level.txt
cappy_grand_creators-0.0.2b0.dist-info/RECORD
