Metadata-Version: 2.1
Name: cappy-grand-creators
Version: 0.0.2b0
Summary: Card and board management API for The Grand Creators
Home-page: https://gitlab.com/grand-creators/cappy
Author: PaytonTheMartian
Author-email: payton.the.martian@gitlab.com
Project-URL: Bug Tracker, https://gitlab.com/grand-creators/cappy/-/issues
Classifier: Programming Language :: Python :: 3
Classifier: License :: OSI Approved :: MIT License
Classifier: Operating System :: OS Independent
Requires-Python: >=3.9
License-File: LICENSE
